{
  "acceptedHRGaps" : 0,
  "acceptedHRSamples" : 0,
  "avgHR" : 58.107244571021717,
  "createdAt" : "2026-06-14T12:42:55Z",
  "csv" : "Documents\/whoop-hr-reference-packages\/whoop-hr-reference-20260614T124255Z-gate-e-overnight-checkpoint-run.csv",
  "durationSeconds" : 10801,
  "externalReferenceRequired" : true,
  "gateDPassed" : false,
  "hrSamples" : 11236,
  "maxAcceptedHRGapSeconds" : 0,
  "observedSeconds" : 10800.704,
  "peakHR" : 85,
  "raw2A37Notifications" : 0,
  "readyForExternalReference" : true,
  "referenceValidated" : false,
  "restingHR" : 47,
  "schema" : 1,
  "sessionEnd" : "2026-06-13T02:41:20Z",
  "sessionLabel" : "gate-e-overnight-checkpoint-run",
  "sessionStart" : "2026-06-12T23:41:19Z",
  "source" : "saved_2a37_hr_points",
  "streamCoveragePercent" : 100
}